sreg.sv
module sreg#(
    parameter ADDRESS_WIDTH=5,
              DATA_WIDTH=32
)(
    input logic clk,
    input logic[ADDRESS_WIDTH-1:0] ad1,
    input logic[ADDRESS_WIDTH-1:0] ad2,
    input logic [ADDRESS_WDITH-1:0]ad3,
    input logic WE3,
    input logic [DATA_WIDTH-1:0] WD3,
    output logic[DATA_WIDTH-1:0] ALUop1,
    output logic[DATA_WIDTH-1:0] regOp2,
    output logic [ADDRESS_WIDTH-1:0]a0
);

//TEMPORARY REFERNEC ETABLE
//ad3 determines which register the ALUout result writes to
logic [DATA_WIDTH-1:0] rom_array [2**ADDRESS_WIDTH-1:0];

//link between ALUout and WD3
//SET POSITION 0 TO 0
//sequential write
always_ff@(posedge clk) begin
    if(WE3)
    rom_array[ad3]<=WD3;
    
end 

//combinatorial read ->combinatorial should be equal
always_comb
    begin
    ALUop1=rom_array[ad1];
    regOp2=rom_array[ad2];
    a0<rom_array[5'b00101]; // this is rom_array 10: //A0 is register 10: abi name, risc v abi: application binary interfcae
    end
endmodule

src.sv
module src(
    parameter=DATA_WIDTH=32
)(
input logic[DATA_WIDTH-1:0] regOp2,
input logic[DATA_WIDTH-1:0] ImmOp,
input logic ALUsrc,
output logic[DATA_WIDTH-1:0] ALUop2
);

assign ALUop2=ALUsrc?ImmOp:regOp2;

endmodule

alu.sv
module alu #(
 parameter DATA_WIDTH=32
 )
 (
    input logic[DATA_WIDTH-1:0] ALUop1,
    input logic[DATA_WIDTH-1:0] ALUop2,
    input logic[2:0] ALUctrl,
    output logic[DATA_WIDTH-1:0] ALUout,//SUM
    output logic EQ

);

always_comb //always comb //case add aluctrl
    case(ALUctrl)
    3'b000:begin
        ALUout = ALUop1+ALUop2;
        EQ= 0; //it will keep the value of eq that it had before so needs to be reset
    end

     //need rs1 and rs2 to be the same.
    3'b111:EQ=(ALUop1 == ALUop2) ; //
    default: ALUout = 0; //what should default case
    endcase


endmodule

alutop.sv
module alutop#(
    parameter ADDRESS_WIDTH=5,
              DATA_WIDTH=32
)(

    input logic clk,
    input logic RegWrite,
    input logic ALUsrc,
    input logic[2:0] ALUctrl,
    input logic[DATA_WIDTH-1:0] immOp,
    
    input logic [ADDRESS_WIDTH-1:0] rs1,
    input logic [ADDRESS_WIDTH-1:0] rs2,
    input logic [ADDRESS_WIDTH-1:0] rd,
    output logic [DATA_WIDTH-1:0]a0,
    output logic[DATA_WIDTH -1:0] ALUout,
    output logic EQ
);
logic[DATA_WIDTH-1:0] ALUop1;
logic[DATA_WIDTH-1:0] regOp2;
logic[DATA_WIDTH-1:0] ALUop2;

alu alulogic(
    .ALUop1(ALUop1),
    .ALUop2(ALUop2),
    .ALUout(ALUout),
    .ALUctrl(ALUctrl),
    .EQ(EQ)

);

src SelectSignal(
    .regOp2(regOp2),
    .ImmOp(immOp),
    .ALUsrc(ALUsrc),
    .ALUop2(ALUop2)
);

sreg regfile(
    .clk(clk),//after dot is internal signal, inside brackets external signal
    .ad1(rs1),
    .ad2(rs2),
    .ad3(rd),
    .WE3(RegWrite),
    .WD3(ALUout),
    .ALUop1(ALUop1),
    .regOp2(regOp2),
    .a0(a0)

);


endmodule

rom.sv
module rom(
    input logic clk,
    input logic [31:0] A,
    output logic [31:0] RD
);

logic [31:0] rom_array [63:0];

initial begin
    $readmemh("InstructionMemory.mem", rom_array);
end;

assign RD = rom_array [A];

endmodule

extend.sv
module extend(
    input logic[1:0] ImmSrc,
    input logic[31:7] Instr,
    output logic[31:0] ImmOp
);

always_comb
    case(ImmSrc)
        2'b00: ImmOp = {{20{Instr[31]}}, Instr[31:20]};
        2'b10: ImmOp = {{20{Instr[31]}}, Instr[7], Instr[30:25], Instr[11:8], 1'b0};
        default: ImmOp = 32'bx;
    endcase

endmodule

ctrlu.sv
module ctrlu(
    input logic EQ,
    input logic [6:0] op;
    input logic [2:0] funct3;
    input logic funct7b5;
    output logic RegWrite,
    output logic [2:0] ALUctrl,
    output logic ALUsrc,
    output logic [1:0] ImmSrc,
    output logic PCsrc
);
logic branch;
logic [7:0] ctrl;
assign {RegWrite, ImmSrc, ALUsrc, ALUctrl, branch} = ctrl;
assign PCsrc = branch & (~EQ); //branch if not equals

always_comb begin
    case(op)
        7'b0010011: //addi
            case(funct3)
                3'b000: ctrl = 8'b10010000;
                default: ctrl = 8'b1001xxx0;
            endcase
        7'b1100011: //bne
            case(funct3)
                3'b001: ctrl = 8'b01000011;
                default: ctrl = 8'b0100xxx1;
            endcase

        default: ctrl = 8'bxxxxxxxx;
    endcase
end

endmodule

controltop.sv
module controltop#(
    parameter ADDRESS_WIDTH=5,
              DATA_WIDTH=32
)(
input logic clk,
input [DATA_WIDTH-1:0] A,
input logic EQ,

output logic RegWrite,
output logic ALUctrl,
output logic ALUsrc,
output logic PCsrc,
output logic [ADDRESS_WIDTH-1:0] rs1,
output logic [ADDRESS_WIDTH-1:0] rs2,
output logic [ADDRESS_WIDTH-1:0] rd,
output logic [DATA_WIDTH-1:0] ImmOp
);

logic [DATA_WIDTH-1:0] RD_instr;
logic [1:0]ImmSrc;

ctrlu controlunit(
.EQ(EQ), //after dot is the internal signal and in the brackets external
.op(RD_instr[6:0]),
.funct3(RD_instr[14:12]),

.ALUctrl(ALUctrl),
.ALUsrc(ALUsrc),
.ImmSrc(ImmSrc),
.PCsrc(PCsrc),
.RegWrite(RegWrite)
);

extend signextend(
.ImmSrc(ImmSrc),
.Instr(RD_instr[31:7]),

.ImmOp(ImmOp)
);

rom instructionmemory(
.clk(clk),
.A(A),

.RD(RD_instr)
);


endmodule

pcreg.sv
module pcreg (
    input logic clk,
    input logic rst,
    input logic [31:0] ImmOp,
    input logic PCsrc,

    output logic [31:0] PC
);

logic [31:0] next_PC;
logic [31:0] inc_PC;
logic [31:0] branch_PC;

assign branch_PC = PC + ImmOp;
assign inc_PC = PC + 4;
assign next_PC = PCsrc ? branch_PC : inc_PC;

always_ff @(posedge clk, posedge rst) begin
    if(rst) PC <= 0;
    else PC <= next_PC;
end


endmodule

simplecpu.sv
module simplecpu#(
    parameter ADDRESS_WIDTH=5,
              DATA_WIDTH=32

)(
    input logic clk,
    input logic rst,
    output logic [DATA_WIDTH-1:0] a0
);

logic [DATA_WIDTH-1:0] ImmOp;
logic [31:0] PC;
logic PCsrc;
logic [DATA_WIDTH-1:0] A;
logic EQ;
logic RegWrite;
logic ALUctrl;
logic ALUsrc;
logic [ADDRESS_WIDTH-1:0] rs1;
logic [ADDRESS_WIDTH-1:0] rs2;
logic [ADDRESS_WIDTH-1:0] rd;
logic ImmSrc;
logic [DATA_WIDTH-1:0] ALUout;



pcreg pc(
    .clk(clk),
    .rst(rst),
    .ImmOp(ImmOp),
    .PCsrc(PCsrc),
    .PC(PC)
);

controltop cu(
    .clk(clk),
    .EQ(EQ), //after dot is the internal signal and in the brackets external
    .ALUctrl(ALUctrl),
    .ALUsrc(ALUsrc),
    .PCsrc(PCsrc),
    .RegWrite(RegWrite),
    .A(PC),
    .rs1(rs1),
    .rs2(rs2),
    .rd(rd),
    .ImmOp(ImmOp)
);

alutop alu(
    .clk(clk),
    .immOp(ImmOp),
    .a0(a0),
    .ALUout(ALUout),
    .RegWrite(RegWrite),
    .ALUsrc(ALUsrc),
    .ALUctrl(ALUctrl),
    .rs1(rs1),
    .rs2(rs2),
    .rd(rd),
    .EQ(EQ)
);





endmodule

simplecpu.vcd
$version Generated by VerilatedVcd $end
$date Thu Nov 24 11:21:40 2022 $end
$timescale 1ps $end

 $scope module TOP $end
  $var wire 32 [ a0 [31:0] $end
  $var wire  1 Y clk $end
  $var wire  1 Z rst $end
  $scope module simplecpu $end
   $var wire 32 _ A [31:0] $end
   $var wire 32 ] ADDRESS_WIDTH [31:0] $end
   $var wire  1 J ALUctrl $end
   $var wire 32 \ ALUout [31:0] $end
   $var wire  1 K ALUsrc $end
   $var wire 32 ^ DATA_WIDTH [31:0] $end
   $var wire  1 H EQ $end
   $var wire 32 E ImmOp [31:0] $end
   $var wire  1 c ImmSrc $end
   $var wire 32 F PC [31:0] $end
   $var wire  1 G PCsrc $end
   $var wire  1 I RegWrite $end
   $var wire 32 [ a0 [31:0] $end
   $var wire  1 Y clk $end
   $var wire  5 b rd [4:0] $end
   $var wire  5 ` rs1 [4:0] $end
   $var wire  5 a rs2 [4:0] $end
   $var wire  1 Z rst $end
   $scope module alu $end
    $var wire 32 ] ADDRESS_WIDTH [31:0] $end
    $var wire  3 L ALUctrl [2:0] $end
    $var wire 32 # ALUop1 [31:0] $end
    $var wire 32 M ALUop2 [31:0] $end
    $var wire 32 \ ALUout [31:0] $end
    $var wire  1 K ALUsrc $end
    $var wire 32 ^ DATA_WIDTH [31:0] $end
    $var wire  1 H EQ $end
    $var wire  1 I RegWrite $end
    $var wire 32 [ a0 [31:0] $end
    $var wire  1 Y clk $end
    $var wire 32 E immOp [31:0] $end
    $var wire  5 b rd [4:0] $end
    $var wire 32 $ regOp2 [31:0] $end
    $var wire  5 ` rs1 [4:0] $end
    $var wire  5 a rs2 [4:0] $end
    $scope module SelectSignal $end
     $var wire 32 M ALUop2 [31:0] $end
     $var wire  1 K ALUsrc $end
     $var wire 32 ^ DATA_WIDTH [31:0] $end
     $var wire 32 E ImmOp [31:0] $end
     $var wire 32 $ regOp2 [31:0] $end
    $upscope $end
    $scope module alulogic $end
     $var wire  3 L ALUctrl [2:0] $end
     $var wire 32 # ALUop1 [31:0] $end
     $var wire 32 M ALUop2 [31:0] $end
     $var wire 32 \ ALUout [31:0] $end
     $var wire 32 ^ DATA_WIDTH [31:0] $end
     $var wire  1 H EQ $end
    $upscope $end
    $scope module regfile $end
     $var wire 32 ] ADDRESS_WIDTH [31:0] $end
     $var wire 32 # ALUop1 [31:0] $end
     $var wire 32 ^ DATA_WIDTH [31:0] $end
     $var wire 32 \ WD3 [31:0] $end
     $var wire  1 I WE3 $end
     $var wire 32 [ a0 [31:0] $end
     $var wire  5 ` ad1 [4:0] $end
     $var wire  5 a ad2 [4:0] $end
     $var wire  5 b ad3 [4:0] $end
     $var wire  1 Y clk $end
     $var wire 32 $ regOp2 [31:0] $end
     $var wire 32 % rom_array[0] [31:0] $end
     $var wire 32 / rom_array[10] [31:0] $end
     $var wire 32 0 rom_array[11] [31:0] $end
     $var wire 32 1 rom_array[12] [31:0] $end
     $var wire 32 2 rom_array[13] [31:0] $end
     $var wire 32 3 rom_array[14] [31:0] $end
     $var wire 32 4 rom_array[15] [31:0] $end
     $var wire 32 5 rom_array[16] [31:0] $end
     $var wire 32 6 rom_array[17] [31:0] $end
     $var wire 32 7 rom_array[18] [31:0] $end
     $var wire 32 8 rom_array[19] [31:0] $end
     $var wire 32 & rom_array[1] [31:0] $end
     $var wire 32 9 rom_array[20] [31:0] $end
     $var wire 32 : rom_array[21] [31:0] $end
     $var wire 32 ; rom_array[22] [31:0] $end
     $var wire 32 < rom_array[23] [31:0] $end
     $var wire 32 = rom_array[24] [31:0] $end
     $var wire 32 > rom_array[25] [31:0] $end
     $var wire 32 ? rom_array[26] [31:0] $end
     $var wire 32 @ rom_array[27] [31:0] $end
     $var wire 32 A rom_array[28] [31:0] $end
     $var wire 32 B rom_array[29] [31:0] $end
     $var wire 32 ' rom_array[2] [31:0] $end
     $var wire 32 C rom_array[30] [31:0] $end
     $var wire 32 D rom_array[31] [31:0] $end
     $var wire 32 ( rom_array[3] [31:0] $end
     $var wire 32 ) rom_array[4] [31:0] $end
     $var wire 32 * rom_array[5] [31:0] $end
     $var wire 32 + rom_array[6] [31:0] $end
     $var wire 32 , rom_array[7] [31:0] $end
     $var wire 32 - rom_array[8] [31:0] $end
     $var wire 32 . rom_array[9] [31:0] $end
    $upscope $end
   $upscope $end
   $scope module cu $end
    $var wire 32 F A [31:0] $end
    $var wire 32 ] ADDRESS_WIDTH [31:0] $end
    $var wire  1 J ALUctrl $end
    $var wire  1 K ALUsrc $end
    $var wire 32 ^ DATA_WIDTH [31:0] $end
    $var wire  1 H EQ $end
    $var wire 32 E ImmOp [31:0] $end
    $var wire  2 O ImmSrc [1:0] $end
    $var wire  1 G PCsrc $end
    $var wire 32 N RD_instr [31:0] $end
    $var wire  1 I RegWrite $end
    $var wire  1 Y clk $end
    $var wire  5 b rd [4:0] $end
    $var wire  5 ` rs1 [4:0] $end
    $var wire  5 a rs2 [4:0] $end
    $scope module controlunit $end
     $var wire  3 R ALUctrl [2:0] $end
     $var wire  1 K ALUsrc $end
     $var wire  1 H EQ $end
     $var wire  2 O ImmSrc [1:0] $end
     $var wire  1 G PCsrc $end
     $var wire  1 I RegWrite $end
     $var wire  1 S branch $end
     $var wire  8 T ctrl [7:0] $end
     $var wire  3 Q funct3 [2:0] $end
     $var wire  7 P op [6:0] $end
    $upscope $end
    $scope module instructionmemory $end
     $var wire 32 F A [31:0] $end
     $var wire 32 N RD [31:0] $end
     $var wire  1 Y clk $end
    $upscope $end
    $scope module signextend $end
     $var wire 32 E ImmOp [31:0] $end
     $var wire  2 O ImmSrc [1:0] $end
     $var wire 25 U Instr [31:7] $end
    $upscope $end
   $upscope $end
   $scope module pc $end
    $var wire 32 E ImmOp [31:0] $end
    $var wire 32 F PC [31:0] $end
    $var wire  1 G PCsrc $end
    $var wire 32 X branch_PC [31:0] $end
    $var wire  1 Y clk $end
    $var wire 32 W inc_PC [31:0] $end
    $var wire 32 V next_PC [31:0] $end
    $var wire  1 Z rst $end
   $upscope $end
  $upscope $end
 $upscope $end
$enddefinitions $end


#0
b00000000000000000000000000000000 #
b00000000000000000000000000000000 $
b00000000000000000000000000000000 %
b00000000000000000000000000000000 &
b00000000000000000000000000000000 '
b00000000000000000000000000000000 (
b00000000000000000000000000000000 )
b00000000000000000000000000000000 *
b00000000000000000000000000000000 +
b00000000000000000000000000000000 ,
b00000000000000000000000000000000 -
b00000000000000000000000000000000 .
b00000000000000000000000000000000 /
b00000000000000000000000000000000 0
b00000000000000000000000000000000 1
b00000000000000000000000000000000 2
b00000000000000000000000000000000 3
b00000000000000000000000000000000 4
b00000000000000000000000000000000 5
b00000000000000000000000000000000 6
b00000000000000000000000000000000 7
b00000000000000000000000000000000 8
b00000000000000000000000000000000 9
b00000000000000000000000000000000 :
b00000000000000000000000000000000 ;
b00000000000000000000000000000000 <
b00000000000000000000000000000000 =
b00000000000000000000000000000000 >
b00000000000000000000000000000000 ?
b00000000000000000000000000000000 @
b00000000000000000000000000000000 A
b00000000000000000000000000000000 B
b00000000000000000000000000000000 C
b00000000000000000000000000000000 D
b00000000000000000000000000000000 E
b00000000000000000000000000000000 F
0G
0H
0I
0J
0K
b000 L
b00000000000000000000000000000000 M
b00000000000000000000000000000000 N
b00 O
b0000000 P
b000 Q
b000 R
0S
b00000000 T
b0000000000000000000000000 U
b00000000000000000000000000000100 V
b00000000000000000000000000000100 W
b00000000000000000000000000000000 X
1Y
1Z
b00000000000000000000000000000000 [
b00000000000000000000000000000000 \
b00000000000000000000000000000101 ]
b00000000000000000000000000100000 ^
b00000000000000000000000000000000 _
b00000 `
b00000 a
b00000 b
0c
#1
b00000000000000000000000011111111 E
1I
1K
b00000000000000000000000011111111 M
b00001111111100000000001100010011 N
b0010011 P
b10010000 T
b0000111111110000000000110 U
b00000000000000000000000011111111 X
0Y
b00000000000000000000000011111111 \
#2
b00000000000000000000000011111111 #
b00000000000000000000000011111111 $
b00000000000000000000000011111111 %
1Y
b00000000000000000000000111111110 \
#3
0Y
#4
b00000000000000000000000111111110 #
b00000000000000000000000111111110 $
b00000000000000000000000111111110 %
1Y
0Z
b00000000000000000000001011111101 \
#5
0Y
#6
b00000000000000000000001011111101 #
b00000000000000000000001011111101 $
b00000000000000000000001011111101 %
b00000000000000000000000000000001 E
b00000000000000000000000000000100 F
b00000000000000000000000000000001 M
b00000000000101011000010110010011 N
b0000000000010101100001011 U
b00000000000000000000000000001000 V
b00000000000000000000000000001000 W
b00000000000000000000000000000101 X
1Y
b00000000000000000000001011111110 \
#7
0Y
#8
b00000000000000000000001011111110 #
b00000000000000000000001011111110 $
b00000000000000000000001011111110 %
b00000000000000000000000000000000 E
b00000000000000000000000000001000 F
0I
0K
b00000000000000000000001011111110 M
b00000000000000000000000000000000 N
b0000000 P
b00000000 T
b0000000000000000000000000 U
b00000000000000000000000000001100 V
b00000000000000000000000000001100 W
b00000000000000000000000000001000 X
1Y
b00000000000000000000010111111100 \
#9
0Y
#10
b00000000000000000000000000001100 F
b00000000000000000000000000010000 V
b00000000000000000000000000010000 W
b00000000000000000000000000001100 X
1Y
#11
0Y
#12
b00000000000000000000000000010000 F
b00000000000000000000000000010100 V
b00000000000000000000000000010100 W
b00000000000000000000000000010000 X
1Y
#13
0Y
#14
b00000000000000000000000000010100 F
b00000000000000000000000000011000 V
b00000000000000000000000000011000 W
b00000000000000000000000000010100 X
1Y
#15
0Y
#16
b00000000000000000000000000011000 F
b00000000000000000000000000011100 V
b00000000000000000000000000011100 W
b00000000000000000000000000011000 X
1Y
#17
0Y
#18
b00000000000000000000000000011100 F
b00000000000000000000000000100000 V
b00000000000000000000000000100000 W
b00000000000000000000000000011100 X
1Y
#19
0Y
#20
b00000000000000000000000000100000 F
b00000000000000000000000000100100 V
b00000000000000000000000000100100 W
b00000000000000000000000000100000 X
1Y
#21
0Y
#22
b00000000000000000000000000100100 F
b00000000000000000000000000101000 V
b00000000000000000000000000101000 W
b00000000000000000000000000100100 X
1Y
#23
0Y
#24
b00000000000000000000000000101000 F
b00000000000000000000000000101100 V
b00000000000000000000000000101100 W
b00000000000000000000000000101000 X
1Y
#25
0Y
#26
b00000000000000000000000000101100 F
b00000000000000000000000000110000 V
b00000000000000000000000000110000 W
b00000000000000000000000000101100 X
1Y
#27
0Y
#28
b00000000000000000000000000110000 F
b00000000000000000000000000110100 V
b00000000000000000000000000110100 W
b00000000000000000000000000110000 X
1Y
#29
0Y
#30
b00000000000000000000000000110100 F
b00000000000000000000000000111000 V
b00000000000000000000000000111000 W
b00000000000000000000000000110100 X
1Y
#31
0Y
#32
b00000000000000000000000000111000 F
b00000000000000000000000000111100 V
b00000000000000000000000000111100 W
b00000000000000000000000000111000 X
1Y
#33
0Y
#34
b00000000000000000000000000111100 F
b00000000000000000000000001000000 V
b00000000000000000000000001000000 W
b00000000000000000000000000111100 X
1Y
#35
0Y
#36
b00000000000000000000000011111111 E
b00000000000000000000000001000000 F
1I
1K
b00000000000000000000000011111111 M
b00001111111100000000001100010011 N
b0010011 P
b10010000 T
b0000111111110000000000110 U
b00000000000000000000000001000100 V
b00000000000000000000000001000100 W
b00000000000000000000000100111111 X
1Y
b00000000000000000000001111111101 \
#37
0Y
#38
b00000000000000000000001111111101 #
b00000000000000000000001111111101 $
b00000000000000000000001111111101 %
b00000000000000000000000000000001 E
b00000000000000000000000001000100 F
b00000000000000000000000000000001 M
b00000000000101011000010110010011 N
b0000000000010101100001011 U
b00000000000000000000000001001000 V
b00000000000000000000000001001000 W
b00000000000000000000000001000101 X
1Y
b00000000000000000000001111111110 \
#39
0Y
#40
b00000000000000000000001111111110 #
b00000000000000000000001111111110 $
b00000000000000000000001111111110 %
b00000000000000000000000000000000 E
b00000000000000000000000001001000 F
0I
0K
b00000000000000000000001111111110 M
b00000000000000000000000000000000 N
b0000000 P
b00000000 T
b0000000000000000000000000 U
b00000000000000000000000001001100 V
b00000000000000000000000001001100 W
b00000000000000000000000001001000 X
1Y
b00000000000000000000011111111100 \
#41
0Y
#42
b00000000000000000000000001001100 F
b00000000000000000000000001010000 V
b00000000000000000000000001010000 W
b00000000000000000000000001001100 X
1Y
#43
0Y
#44
b00000000000000000000000001010000 F
b00000000000000000000000001010100 V
b00000000000000000000000001010100 W
b00000000000000000000000001010000 X
1Y
#45
0Y
#46
b00000000000000000000000001010100 F
b00000000000000000000000001011000 V
b00000000000000000000000001011000 W
b00000000000000000000000001010100 X
1Y
#47
0Y
#48
b00000000000000000000000001011000 F
b00000000000000000000000001011100 V
b00000000000000000000000001011100 W
b00000000000000000000000001011000 X
1Y
#49
0Y
#50
b00000000000000000000000001011100 F
b00000000000000000000000001100000 V
b00000000000000000000000001100000 W
b00000000000000000000000001011100 X
1Y
#51
0Y
#52
b00000000000000000000000001100000 F
b00000000000000000000000001100100 V
b00000000000000000000000001100100 W
b00000000000000000000000001100000 X
1Y
#53
0Y
#54
b00000000000000000000000001100100 F
b00000000000000000000000001101000 V
b00000000000000000000000001101000 W
b00000000000000000000000001100100 X
1Y
#55
0Y
#56
b00000000000000000000000001101000 F
b00000000000000000000000001101100 V
b00000000000000000000000001101100 W
b00000000000000000000000001101000 X
1Y
#57
0Y
#58
b00000000000000000000000001101100 F
b00000000000000000000000001110000 V
b00000000000000000000000001110000 W
b00000000000000000000000001101100 X
1Y
#59
0Y
#60
b00000000000000000000000001110000 F
b00000000000000000000000001110100 V
b00000000000000000000000001110100 W
b00000000000000000000000001110000 X
1Y
#61
0Y
#62
b00000000000000000000000001110100 F
b00000000000000000000000001111000 V
b00000000000000000000000001111000 W
b00000000000000000000000001110100 X
1Y
#63
0Y
#64
b00000000000000000000000001111000 F
b00000000000000000000000001111100 V
b00000000000000000000000001111100 W
b00000000000000000000000001111000 X
1Y
#65
0Y
#66
b00000000000000000000000001111100 F
b00000000000000000000000010000000 V
b00000000000000000000000010000000 W
b00000000000000000000000001111100 X
1Y
#67
0Y
#68
b00000000000000000000000011111111 E
b00000000000000000000000010000000 F
1I
1K
b00000000000000000000000011111111 M
b00001111111100000000001100010011 N
b0010011 P
b10010000 T
b0000111111110000000000110 U
b00000000000000000000000010000100 V
b00000000000000000000000010000100 W
b00000000000000000000000101111111 X
1Y
b00000000000000000000010011111101 \
#69
0Y
#70
b00000000000000000000010011111101 #
b00000000000000000000010011111101 $
b00000000000000000000010011111101 %
b00000000000000000000000000000001 E
b00000000000000000000000010000100 F
b00000000000000000000000000000001 M
b00000000000101011000010110010011 N
b0000000000010101100001011 U
b00000000000000000000000010001000 V
b00000000000000000000000010001000 W
b00000000000000000000000010000101 X
1Y
b00000000000000000000010011111110 \
#71
0Y
#72
b00000000000000000000010011111110 #
b00000000000000000000010011111110 $
b00000000000000000000010011111110 %
b00000000000000000000000000000000 E
b00000000000000000000000010001000 F
0I
0K
b00000000000000000000010011111110 M
b00000000000000000000000000000000 N
b0000000 P
b00000000 T
b0000000000000000000000000 U
b00000000000000000000000010001100 V
b00000000000000000000000010001100 W
b00000000000000000000000010001000 X
1Y
b00000000000000000000100111111100 \
#73
0Y
#74
b00000000000000000000000010001100 F
b00000000000000000000000010010000 V
b00000000000000000000000010010000 W
b00000000000000000000000010001100 X
1Y
#75
0Y
#76
b00000000000000000000000010010000 F
b00000000000000000000000010010100 V
b00000000000000000000000010010100 W
b00000000000000000000000010010000 X
1Y
#77
0Y
#78
b00000000000000000000000010010100 F
b00000000000000000000000010011000 V
b00000000000000000000000010011000 W
b00000000000000000000000010010100 X
1Y
#79
0Y
#80
b00000000000000000000000010011000 F
b00000000000000000000000010011100 V
b00000000000000000000000010011100 W
b00000000000000000000000010011000 X
1Y
#81
0Y
#82
b00000000000000000000000010011100 F
b00000000000000000000000010100000 V
b00000000000000000000000010100000 W
b00000000000000000000000010011100 X
1Y
#83
0Y
#84
b00000000000000000000000010100000 F
b00000000000000000000000010100100 V
b00000000000000000000000010100100 W
b00000000000000000000000010100000 X
1Y
#85
0Y
#86
b00000000000000000000000010100100 F
b00000000000000000000000010101000 V
b00000000000000000000000010101000 W
b00000000000000000000000010100100 X
1Y
#87
0Y
#88
b00000000000000000000000010101000 F
b00000000000000000000000010101100 V
b00000000000000000000000010101100 W
b00000000000000000000000010101000 X
1Y
#89
0Y
#90
b00000000000000000000000010101100 F
b00000000000000000000000010110000 V
b00000000000000000000000010110000 W
b00000000000000000000000010101100 X
1Y
#91
0Y
#92
b00000000000000000000000010110000 F
b00000000000000000000000010110100 V
b00000000000000000000000010110100 W
b00000000000000000000000010110000 X
1Y
#93
0Y
#94
b00000000000000000000000010110100 F
b00000000000000000000000010111000 V
b00000000000000000000000010111000 W
b00000000000000000000000010110100 X
1Y
#95
0Y
#96
b00000000000000000000000010111000 F
b00000000000000000000000010111100 V
b00000000000000000000000010111100 W
b00000000000000000000000010111000 X
1Y
#97
0Y
#98
b00000000000000000000000010111100 F
b00000000000000000000000011000000 V
b00000000000000000000000011000000 W
b00000000000000000000000010111100 X
1Y
#99
0Y
#100
b00000000000000000000000011111111 E
b00000000000000000000000011000000 F
1I
1K
b00000000000000000000000011111111 M
b00001111111100000000001100010011 N
b0010011 P
b10010000 T
b0000111111110000000000110 U
b00000000000000000000000011000100 V
b00000000000000000000000011000100 W
b00000000000000000000000110111111 X
1Y
b00000000000000000000010111111101 \
#101
0Y
#102
b00000000000000000000010111111101 #
b00000000000000000000010111111101 $
b00000000000000000000010111111101 %
b00000000000000000000000000000001 E
b00000000000000000000000011000100 F
b00000000000000000000000000000001 M
b00000000000101011000010110010011 N
b0000000000010101100001011 U
b00000000000000000000000011001000 V
b00000000000000000000000011001000 W
b00000000000000000000000011000101 X
1Y
b00000000000000000000010111111110 \
#103
0Y
#104
b00000000000000000000010111111110 #
b00000000000000000000010111111110 $
b00000000000000000000010111111110 %
b00000000000000000000000000000000 E
b00000000000000000000000011001000 F
0I
0K
b00000000000000000000010111111110 M
b00000000000000000000000000000000 N
b0000000 P
b00000000 T
b0000000000000000000000000 U
b00000000000000000000000011001100 V
b00000000000000000000000011001100 W
b00000000000000000000000011001000 X
1Y
b00000000000000000000101111111100 \
#105
0Y
#106
b00000000000000000000000011001100 F
b00000000000000000000000011010000 V
b00000000000000000000000011010000 W
b00000000000000000000000011001100 X
1Y
#107
0Y
#108
b00000000000000000000000011010000 F
b00000000000000000000000011010100 V
b00000000000000000000000011010100 W
b00000000000000000000000011010000 X
1Y
#109
0Y
#110
b00000000000000000000000011010100 F
b00000000000000000000000011011000 V
b00000000000000000000000011011000 W
b00000000000000000000000011010100 X
1Y
#111
0Y
#112
b00000000000000000000000011011000 F
b00000000000000000000000011011100 V
b00000000000000000000000011011100 W
b00000000000000000000000011011000 X
1Y
#113
0Y
#114
b00000000000000000000000011011100 F
b00000000000000000000000011100000 V
b00000000000000000000000011100000 W
b00000000000000000000000011011100 X
1Y
#115
0Y
#116
b00000000000000000000000011100000 F
b00000000000000000000000011100100 V
b00000000000000000000000011100100 W
b00000000000000000000000011100000 X
1Y
#117
0Y
#118
b00000000000000000000000011100100 F
b00000000000000000000000011101000 V
b00000000000000000000000011101000 W
b00000000000000000000000011100100 X
1Y
#119
0Y
#120
b00000000000000000000000011101000 F
b00000000000000000000000011101100 V
b00000000000000000000000011101100 W
b00000000000000000000000011101000 X
1Y
#121
0Y
#122
b00000000000000000000000011101100 F
b00000000000000000000000011110000 V
b00000000000000000000000011110000 W
b00000000000000000000000011101100 X
1Y
#123
0Y
#124
b00000000000000000000000011110000 F
b00000000000000000000000011110100 V
b00000000000000000000000011110100 W
b00000000000000000000000011110000 X
1Y
#125
0Y
#126
b00000000000000000000000011110100 F
b00000000000000000000000011111000 V
b00000000000000000000000011111000 W
b00000000000000000000000011110100 X
1Y
#127
0Y
#128
b00000000000000000000000011111000 F
b00000000000000000000000011111100 V
b00000000000000000000000011111100 W
b00000000000000000000000011111000 X
1Y
#129
0Y
#130
b00000000000000000000000011111100 F
b00000000000000000000000100000000 V
b00000000000000000000000100000000 W
b00000000000000000000000011111100 X
1Y
#131
0Y
#132
b00000000000000000000000011111111 E
b00000000000000000000000100000000 F
1I
1K
b00000000000000000000000011111111 M
b00001111111100000000001100010011 N
b0010011 P
b10010000 T
b0000111111110000000000110 U
b00000000000000000000000100000100 V
b00000000000000000000000100000100 W
b00000000000000000000000111111111 X
1Y
b00000000000000000000011011111101 \
#133
0Y
#134
b00000000000000000000011011111101 #
b00000000000000000000011011111101 $
b00000000000000000000011011111101 %
b00000000000000000000000000000001 E
b00000000000000000000000100000100 F
b00000000000000000000000000000001 M
b00000000000101011000010110010011 N
b0000000000010101100001011 U
b00000000000000000000000100001000 V
b00000000000000000000000100001000 W
b00000000000000000000000100000101 X
1Y
b00000000000000000000011011111110 \
#135
0Y
#136
b00000000000000000000011011111110 #
b00000000000000000000011011111110 $
b00000000000000000000011011111110 %
b00000000000000000000000000000000 E
b00000000000000000000000100001000 F
0I
0K
b00000000000000000000011011111110 M
b00000000000000000000000000000000 N
b0000000 P
b00000000 T
b0000000000000000000000000 U
b00000000000000000000000100001100 V
b00000000000000000000000100001100 W
b00000000000000000000000100001000 X
1Y
b00000000000000000000110111111100 \
#137
0Y
#138
b00000000000000000000000100001100 F
b00000000000000000000000100010000 V
b00000000000000000000000100010000 W
b00000000000000000000000100001100 X
1Y
#139
0Y
#140
b00000000000000000000000100010000 F
b00000000000000000000000100010100 V
b00000000000000000000000100010100 W
b00000000000000000000000100010000 X
1Y
#141
0Y
#142
b00000000000000000000000100010100 F
b00000000000000000000000100011000 V
b00000000000000000000000100011000 W
b00000000000000000000000100010100 X
1Y
#143
0Y
#144
b00000000000000000000000100011000 F
b00000000000000000000000100011100 V
b00000000000000000000000100011100 W
b00000000000000000000000100011000 X
1Y
#145
0Y
#146
b00000000000000000000000100011100 F
b00000000000000000000000100100000 V
b00000000000000000000000100100000 W
b00000000000000000000000100011100 X
1Y
#147
0Y
#148
b00000000000000000000000100100000 F
b00000000000000000000000100100100 V
b00000000000000000000000100100100 W
b00000000000000000000000100100000 X
1Y
#149
0Y
#150
b00000000000000000000000100100100 F
b00000000000000000000000100101000 V
b00000000000000000000000100101000 W
b00000000000000000000000100100100 X
1Y
#151
0Y
#152
b00000000000000000000000100101000 F
b00000000000000000000000100101100 V
b00000000000000000000000100101100 W
b00000000000000000000000100101000 X
1Y
#153
0Y
