sreg.sv
module sreg#(
    parameter ADDRESS_WIDTH=5,
              DATA_WIDTH=32
)(
    input logic clk,
    input logic[ADDRESS_WIDTH-1:0] ad1,
    input logic[ADDRESS_WIDTH-1:0] ad2,
    input logic [ADDRESS_WDITH-1:0]ad3,
    input logic WE3,
    input logic [DATA_WIDTH-1:0] WD3,
    output logic[DATA_WIDTH-1:0] ALUop1,
    output logic[DATA_WIDTH-1:0] regOp2,
    output logic [ADDRESS_WIDTH-1:0]a0
);

//TEMPORARY REFERNEC ETABLE
//ad3 determines which register the ALUout result writes to
logic [DATA_WIDTH-1:0] rom_array [2**ADDRESS_WIDTH-1:0];

//link between ALUout and WD3
//SET POSITION 0 TO 0
//sequential write
always_ff@(posedge clk) begin
    if(WE3)
    rom_array[ad3]<=WD3;
    
end 

//combinatorial read ->combinatorial should be equal
always_comb
    begin
    ALUop1=rom_array[ad1];
    regOp2=rom_array[ad2];
    a0<rom_array[5'b00101]; // this is rom_array 10: //A0 is register 10: abi name, risc v abi: application binary interfcae
    end
endmodule

src.sv
module src(
    parameter=DATA_WIDTH=32
)(
input logic[DATA_WIDTH-1:0] regOp2,
input logic[DATA_WIDTH-1:0] ImmOp,
input logic ALUsrc,
output logic[DATA_WIDTH-1:0] ALUop2
);

assign ALUop2=ALUsrc?ImmOp:regOp2;

endmodule

alu.sv
module alu #(
 parameter DATA_WIDTH=32
 )
 (
    input logic[DATA_WIDTH-1:0] ALUop1,
    input logic[DATA_WIDTH-1:0] ALUop2,
    input logic[2:0] ALUctrl,
    output logic[DATA_WIDTH-1:0] ALUout,//SUM
    output logic EQ

);

always_comb //always comb //case add aluctrl
    case(ALUctrl)
    3'b000:begin
        ALUout = ALUop1+ALUop2;
        EQ= 0; //it will keep the value of eq that it had before so needs to be reset
    end

     //need rs1 and rs2 to be the same.
    3'b111:EQ=(ALUop1 == ALUop2) ; //
    default: ALUout = 0; //what should default case
    endcase


endmodule

alutop.sv
module alutop#(
    parameter ADDRESS_WIDTH=5,
              DATA_WIDTH=32
)(

    input logic clk,
    input logic RegWrite,
    input logic ALUsrc,
    input logic[2:0] ALUctrl,
    input logic[DATA_WIDTH-1:0] immOp,
    
    input logic [ADDRESS_WIDTH-1:0] rs1,
    input logic [ADDRESS_WIDTH-1:0] rs2,
    input logic [ADDRESS_WIDTH-1:0] rd,
    output logic [DATA_WIDTH-1:0]a0,
    output logic[DATA_WIDTH -1:0] ALUout,
    output logic EQ
);
logic[DATA_WIDTH-1:0] ALUop1;
logic[DATA_WIDTH-1:0] regOp2;
logic[DATA_WIDTH-1:0] ALUop2;

alu alulogic(
    .ALUop1(ALUop1),
    .ALUop2(ALUop2),
    .ALUout(ALUout),
    .ALUctrl(ALUctrl),
    .EQ(EQ)

);

src SelectSignal(
    .regOp2(regOp2),
    .ImmOp(immOp),
    .ALUsrc(ALUsrc),
    .ALUop2(ALUop2)
);

sreg regfile(
    .clk(clk),//after dot is internal signal, inside brackets external signal
    .ad1(rs1),
    .ad2(rs2),
    .ad3(rd),
    .WE3(RegWrite),
    .WD3(ALUout),
    .ALUop1(ALUop1),
    .regOp2(regOp2),
    .a0(a0)

);


endmodule

rom.sv
module rom(
    input logic [31:0] A,
    output logic [31:0] RD
);

logic [7:0] rom_array [900:0];

initial begin
    $readmemh("InstructionMemory.mem", rom_array);
end;

assign RD = {rom_array[A], rom_array[A+1], rom_array[A+2], rom_array[A+3]};

endmodule

extend.sv
module extend(
    input logic[1:0] ImmSrc,
    input logic[31:0] Instr,
    output logic[31:0] ImmOp
);

always_comb begin
    case(ImmSrc)
        2'b00: ImmOp = {{20{Instr[31]}}, Instr[31:20]};
        2'b10: ImmOp = {{20{Instr[31]}}, Instr[7], Instr[30:25], Instr[11:8], 1'b0};
        default: ImmOp = 32'bx;
    endcase
end

endmodule

ctrlu.sv
module ctrlu(
    input logic EQ,
    input logic [6:0] op;
    input logic [2:0] funct3;
    input logic funct7b5;
    output logic RegWrite,
    output logic [2:0] ALUctrl,
    output logic ALUsrc,
    output logic [1:0] ImmSrc,
    output logic PCsrc
);
logic branch;
logic [7:0] ctrl;
assign {RegWrite, ImmSrc, ALUsrc, ALUctrl, branch} = ctrl;
assign PCsrc = branch & (~EQ); //branch if not equals

always_comb begin
    case(op)
        7'b0010011: //addi
            case(funct3)
                3'b000: ctrl = 8'b10010000;
                default: ctrl = 8'b1001xxx0;
            endcase
        7'b1100011: //bne
            case(funct3)
                3'b001: ctrl = 8'b01000011;
                default: ctrl = 8'b0100xxx1;
            endcase

        default: ctrl = 8'bxxxxxxxx;
    endcase
end

endmodule

controltop.sv
module controltop#(
    parameter ADDRESS_WIDTH=5,
              DATA_WIDTH=32
)(
input [DATA_WIDTH-1:0] A,
input logic EQ,

output logic RegWrite,
output logic [2:0] ALUctrl,
output logic ALUsrc,
output logic PCsrc,
output logic [ADDRESS_WIDTH-1:0] rs1,
output logic [ADDRESS_WIDTH-1:0] rs2,
output logic [ADDRESS_WIDTH-1:0] rd,
output logic [DATA_WIDTH-1:0] ImmOp
);

logic [DATA_WIDTH-1:0] RD_instr;
logic [1:0] ImmSrc;

assign rs1 = RD_instr[19:15];
assign rs2 = RD_instr[24:20];
assign rd = RD_instr[11:7];

ctrlu controlunit(
.EQ(EQ), //after dot is the internal signal and in the brackets external
.op(RD_instr[6:0]),
.funct3(RD_instr[14:12]),

.ALUctrl(ALUctrl),
.ALUsrc(ALUsrc),
.ImmSrc(ImmSrc),
.PCsrc(PCsrc),
.RegWrite(RegWrite)
);

extend signextend(
.ImmSrc(ImmSrc),
.ImmOp(ImmOp),
.Instr(RD_instr[31:0])
);

rom instructionmemory(
.A(A),

.RD(RD_instr)
);


endmodule

pcreg.sv
module pcreg (
    input logic clk,
    input logic rst,
    input logic [31:0] ImmOp,
    input logic PCsrc,

    output logic [31:0] PC
);

logic [31:0] next_PC;
logic [31:0] inc_PC;
logic [31:0] branch_PC;

assign branch_PC = PC + ImmOp;
assign inc_PC = PC + 4;
assign next_PC = PCsrc ? branch_PC : inc_PC;

always_ff @(posedge clk, posedge rst) begin
    if(rst) PC <= 0;
    else PC <= next_PC;
end


endmodule

simplecpu.sv
module simplecpu#(
    parameter ADDRESS_WIDTH=5,
              DATA_WIDTH=32

)(
    input logic clk,
    input logic rst,
    output logic [DATA_WIDTH-1:0] a0,
    output logic [DATA_WIDTH-1:0] ALUout

);

logic [DATA_WIDTH-1:0] ImmOp;
logic [31:0] PC;
logic PCsrc;
// logic [DATA_WIDTH-1:0] A;
logic EQ;
logic RegWrite;
logic [2:0] ALUctrl;
logic ALUsrc;
logic [ADDRESS_WIDTH-1:0] rs1;
logic [ADDRESS_WIDTH-1:0] rs2;
logic [ADDRESS_WIDTH-1:0] rd;

pcreg pc(
    .clk(clk),
    .rst(rst),
    .ImmOp(ImmOp),
    .PCsrc(PCsrc),
    .PC(PC)
);

controltop cu(
    .EQ(EQ), //after dot is the internal signal and in the brackets external
    .ALUctrl(ALUctrl),
    .ALUsrc(ALUsrc),
    .PCsrc(PCsrc),
    .RegWrite(RegWrite),
    .A(PC),
    .rs1(rs1),
    .rs2(rs2),
    .rd(rd),
    .ImmOp(ImmOp)
);

alutop alu(
    .clk(clk),
    .immOp(ImmOp),
    .a0(a0),
    .ALUout(ALUout),
    .RegWrite(RegWrite),
    .ALUsrc(ALUsrc),
    .ALUctrl(ALUctrl),
    .rs1(rs1),
    .rs2(rs2),
    .rd(rd),
    .EQ(EQ)
);





endmodule

simplecpu.vcd
$version Generated by VerilatedVcd $end
$date Fri Nov 25 11:40:19 2022 $end
$timescale 1ps $end

 $scope module TOP $end
  $var wire 32 W ALUout [31:0] $end
  $var wire 32 V a0 [31:0] $end
  $var wire  1 T clk $end
  $var wire  1 U rst $end
  $scope module simplecpu $end
   $var wire 32 ] ADDRESS_WIDTH [31:0] $end
   $var wire  3 G ALUctrl [2:0] $end
   $var wire 32 W ALUout [31:0] $end
   $var wire  1 H ALUsrc $end
   $var wire 32 ^ DATA_WIDTH [31:0] $end
   $var wire  1 E EQ $end
   $var wire 32 C ImmOp [31:0] $end
   $var wire 32 X PC [31:0] $end
   $var wire  1 D PCsrc $end
   $var wire  1 F RegWrite $end
   $var wire 32 V a0 [31:0] $end
   $var wire  1 T clk $end
   $var wire  5 K rd [4:0] $end
   $var wire  5 I rs1 [4:0] $end
   $var wire  5 J rs2 [4:0] $end
   $var wire  1 U rst $end
   $scope module alu $end
    $var wire 32 ] ADDRESS_WIDTH [31:0] $end
    $var wire  3 G ALUctrl [2:0] $end
    $var wire 32 L ALUop1 [31:0] $end
    $var wire 32 M ALUop2 [31:0] $end
    $var wire 32 W ALUout [31:0] $end
    $var wire  1 H ALUsrc $end
    $var wire 32 ^ DATA_WIDTH [31:0] $end
    $var wire  1 E EQ $end
    $var wire  1 F RegWrite $end
    $var wire 32 V a0 [31:0] $end
    $var wire  1 T clk $end
    $var wire 32 C immOp [31:0] $end
    $var wire  5 K rd [4:0] $end
    $var wire 32 Y regOp2 [31:0] $end
    $var wire  5 I rs1 [4:0] $end
    $var wire  5 J rs2 [4:0] $end
    $scope module SelectSignal $end
     $var wire 32 M ALUop2 [31:0] $end
     $var wire  1 H ALUsrc $end
     $var wire 32 ^ DATA_WIDTH [31:0] $end
     $var wire 32 C ImmOp [31:0] $end
     $var wire 32 Y regOp2 [31:0] $end
    $upscope $end
    $scope module alulogic $end
     $var wire  3 G ALUctrl [2:0] $end
     $var wire 32 L ALUop1 [31:0] $end
     $var wire 32 M ALUop2 [31:0] $end
     $var wire 32 W ALUout [31:0] $end
     $var wire 32 ^ DATA_WIDTH [31:0] $end
     $var wire  1 E EQ $end
    $upscope $end
    $scope module regfile $end
     $var wire 32 ] ADDRESS_WIDTH [31:0] $end
     $var wire 32 L ALUop1 [31:0] $end
     $var wire 32 ^ DATA_WIDTH [31:0] $end
     $var wire 32 W WD3 [31:0] $end
     $var wire  1 F WE3 $end
     $var wire 32 V a0 [31:0] $end
     $var wire  5 I ad1 [4:0] $end
     $var wire  5 J ad2 [4:0] $end
     $var wire  5 K ad3 [4:0] $end
     $var wire  1 T clk $end
     $var wire 32 Y regOp2 [31:0] $end
     $var wire 32 # rom_array[0] [31:0] $end
     $var wire 32 - rom_array[10] [31:0] $end
     $var wire 32 . rom_array[11] [31:0] $end
     $var wire 32 / rom_array[12] [31:0] $end
     $var wire 32 0 rom_array[13] [31:0] $end
     $var wire 32 1 rom_array[14] [31:0] $end
     $var wire 32 2 rom_array[15] [31:0] $end
     $var wire 32 3 rom_array[16] [31:0] $end
     $var wire 32 4 rom_array[17] [31:0] $end
     $var wire 32 5 rom_array[18] [31:0] $end
     $var wire 32 6 rom_array[19] [31:0] $end
     $var wire 32 $ rom_array[1] [31:0] $end
     $var wire 32 7 rom_array[20] [31:0] $end
     $var wire 32 8 rom_array[21] [31:0] $end
     $var wire 32 9 rom_array[22] [31:0] $end
     $var wire 32 : rom_array[23] [31:0] $end
     $var wire 32 ; rom_array[24] [31:0] $end
     $var wire 32 < rom_array[25] [31:0] $end
     $var wire 32 = rom_array[26] [31:0] $end
     $var wire 32 > rom_array[27] [31:0] $end
     $var wire 32 ? rom_array[28] [31:0] $end
     $var wire 32 @ rom_array[29] [31:0] $end
     $var wire 32 % rom_array[2] [31:0] $end
     $var wire 32 A rom_array[30] [31:0] $end
     $var wire 32 B rom_array[31] [31:0] $end
     $var wire 32 & rom_array[3] [31:0] $end
     $var wire 32 ' rom_array[4] [31:0] $end
     $var wire 32 ( rom_array[5] [31:0] $end
     $var wire 32 ) rom_array[6] [31:0] $end
     $var wire 32 * rom_array[7] [31:0] $end
     $var wire 32 + rom_array[8] [31:0] $end
     $var wire 32 , rom_array[9] [31:0] $end
    $upscope $end
   $upscope $end
   $scope module cu $end
    $var wire 32 X A [31:0] $end
    $var wire 32 ] ADDRESS_WIDTH [31:0] $end
    $var wire  3 G ALUctrl [2:0] $end
    $var wire  1 H ALUsrc $end
    $var wire 32 ^ DATA_WIDTH [31:0] $end
    $var wire  1 E EQ $end
    $var wire 32 C ImmOp [31:0] $end
    $var wire  2 O ImmSrc [1:0] $end
    $var wire  1 D PCsrc $end
    $var wire 32 N RD_instr [31:0] $end
    $var wire  1 F RegWrite $end
    $var wire  5 K rd [4:0] $end
    $var wire  5 I rs1 [4:0] $end
    $var wire  5 J rs2 [4:0] $end
    $scope module controlunit $end
     $var wire  3 G ALUctrl [2:0] $end
     $var wire  1 H ALUsrc $end
     $var wire  1 E EQ $end
     $var wire  2 O ImmSrc [1:0] $end
     $var wire  1 D PCsrc $end
     $var wire  1 F RegWrite $end
     $var wire  1 R branch $end
     $var wire  8 S ctrl [7:0] $end
     $var wire  3 Q funct3 [2:0] $end
     $var wire  7 P op [6:0] $end
    $upscope $end
    $scope module instructionmemory $end
     $var wire 32 X A [31:0] $end
     $var wire 32 N RD [31:0] $end
    $upscope $end
    $scope module signextend $end
     $var wire 32 C ImmOp [31:0] $end
     $var wire  2 O ImmSrc [1:0] $end
     $var wire 32 N Instr [31:0] $end
    $upscope $end
   $upscope $end
   $scope module pc $end
    $var wire 32 C ImmOp [31:0] $end
    $var wire 32 X PC [31:0] $end
    $var wire  1 D PCsrc $end
    $var wire 32 \ branch_PC [31:0] $end
    $var wire  1 T clk $end
    $var wire 32 [ inc_PC [31:0] $end
    $var wire 32 Z next_PC [31:0] $end
    $var wire  1 U rst $end
   $upscope $end
  $upscope $end
 $upscope $end
$enddefinitions $end


#0
b00000000000000000000000000000000 #
b00000000000000000000000000000000 $
b00000000000000000000000000000000 %
b00000000000000000000000000000000 &
b00000000000000000000000000000000 '
b00000000000000000000000000000000 (
b00000000000000000000000000000000 )
b00000000000000000000000000000000 *
b00000000000000000000000000000000 +
b00000000000000000000000000000000 ,
b00000000000000000000000000000000 -
b00000000000000000000000000000000 .
b00000000000000000000000000000000 /
b00000000000000000000000000000000 0
b00000000000000000000000000000000 1
b00000000000000000000000000000000 2
b00000000000000000000000000000000 3
b00000000000000000000000000000000 4
b00000000000000000000000000000000 5
b00000000000000000000000000000000 6
b00000000000000000000000000000000 7
b00000000000000000000000000000000 8
b00000000000000000000000000000000 9
b00000000000000000000000000000000 :
b00000000000000000000000000000000 ;
b00000000000000000000000000000000 <
b00000000000000000000000000000000 =
b00000000000000000000000000000000 >
b00000000000000000000000000000000 ?
b00000000000000000000000000000000 @
b00000000000000000000000000000000 A
b00000000000000000000000000000000 B
b00000000000000000000000000000000 C
0D
0E
0F
b000 G
0H
b00000 I
b00000 J
b00000 K
b00000000000000000000000000000000 L
b00000000000000000000000000000000 M
b00000000000000000000000000000000 N
b00 O
b0000000 P
b000 Q
0R
b00000000 S
1T
0U
b00000000000000000000000000000000 V
b00000000000000000000000000000000 W
b00000000000000000000000000000000 X
b00000000000000000000000000000000 Y
b00000000000000000000000000000100 Z
b00000000000000000000000000000100 [
b00000000000000000000000000000000 \
b00000000000000000000000000000101 ]
b00000000000000000000000000100000 ^
#1
b00000000000000000000000011111111 C
1F
1H
b11111 J
b00110 K
b00001111111100000000001100010011 N
b0010011 P
b10010000 S
0T
b00000000000000000000000011111111 \
#2
b00000000000000000000000000000000 C
b00000 J
b01010 K
b00000000000000000000010100010011 N
1T
b00000000000000000000000000000100 X
b00000000000000000000000000001000 Z
b00000000000000000000000000001000 [
b00000000000000000000000000000100 \
#3
0T
#4
b01011 K
b00000000000000000000010110010011 N
1T
b00000000000000000000000000001000 X
b00000000000000000000000000001100 Z
b00000000000000000000000000001100 [
b00000000000000000000000000001000 \
#5
0T
#6
b01011 I
b01010 K
b00000000000001011000010100010011 N
1T
b00000000000000000000000000001100 X
b00000000000000000000000000010000 Z
b00000000000000000000000000010000 [
b00000000000000000000000000001100 \
#7
0T
#8
b00000000000000000000000000000001 C
b00001 J
b01011 K
b00000000000101011000010110010011 N
1T
b00000000000000000000000000010000 X
b00000000000000000000000000010100 Z
b00000000000000000000000000010100 [
b00000000000000000000000000010001 \
#9
0T
#10
b11111111111111111111111111111000 C
1D
0F
b001 G
0H
b00110 J
b11001 K
b11111111111111111111111111111000 M
b11111110011001011001110011100011 N
b10 O
b1100011 P
b001 Q
1R
b01000011 S
1T
b00000000000000000000000000010100 X
b00000000000000000000000000001100 Z
b00000000000000000000000000011000 [
b00000000000000000000000000001100 \
#11
0T
#12
b00000000000000000000000000000000 C
0D
1F
b000 G
1H
b00000 J
b01010 K
b00000000000000000000000000000000 M
b00000000000001011000010100010011 N
b00 O
b0010011 P
b000 Q
0R
b10010000 S
1T
b00000000000000000000000000001100 X
b00000000000000000000000000010000 Z
b00000000000000000000000000010000 [
#13
0T
#14
b00000000000000000000000000000001 C
b00001 J
b01011 K
b00000000000101011000010110010011 N
1T
b00000000000000000000000000010000 X
b00000000000000000000000000010100 Z
b00000000000000000000000000010100 [
b00000000000000000000000000010001 \
#15
0T
#16
b11111111111111111111111111111000 C
1D
0F
b001 G
0H
b00110 J
b11001 K
b11111111111111111111111111111000 M
b11111110011001011001110011100011 N
b10 O
b1100011 P
b001 Q
1R
b01000011 S
1T
b00000000000000000000000000010100 X
b00000000000000000000000000001100 Z
b00000000000000000000000000011000 [
b00000000000000000000000000001100 \
#17
0T
#18
b00000000000000000000000000000000 C
0D
1F
b000 G
1H
b00000 J
b01010 K
b00000000000000000000000000000000 M
b00000000000001011000010100010011 N
b00 O
b0010011 P
b000 Q
0R
b10010000 S
1T
b00000000000000000000000000001100 X
b00000000000000000000000000010000 Z
b00000000000000000000000000010000 [
#19
0T
#20
b00000000000000000000000000000001 C
b00001 J
b01011 K
b00000000000101011000010110010011 N
1T
b00000000000000000000000000010000 X
b00000000000000000000000000010100 Z
b00000000000000000000000000010100 [
b00000000000000000000000000010001 \
#21
0T
#22
b11111111111111111111111111111000 C
1D
0F
b001 G
0H
b00110 J
b11001 K
b11111111111111111111111111111000 M
b11111110011001011001110011100011 N
b10 O
b1100011 P
b001 Q
1R
b01000011 S
1T
b00000000000000000000000000010100 X
b00000000000000000000000000001100 Z
b00000000000000000000000000011000 [
b00000000000000000000000000001100 \
#23
0T
#24
b00000000000000000000000000000000 C
0D
1F
b000 G
1H
b00000 J
b01010 K
b00000000000000000000000000000000 M
b00000000000001011000010100010011 N
b00 O
b0010011 P
b000 Q
0R
b10010000 S
1T
b00000000000000000000000000001100 X
b00000000000000000000000000010000 Z
b00000000000000000000000000010000 [
#25
0T
#26
b00000000000000000000000000000001 C
b00001 J
b01011 K
b00000000000101011000010110010011 N
1T
b00000000000000000000000000010000 X
b00000000000000000000000000010100 Z
b00000000000000000000000000010100 [
b00000000000000000000000000010001 \
#27
0T
#28
b11111111111111111111111111111000 C
1D
0F
b001 G
0H
b00110 J
b11001 K
b11111111111111111111111111111000 M
b11111110011001011001110011100011 N
b10 O
b1100011 P
b001 Q
1R
b01000011 S
1T
b00000000000000000000000000010100 X
b00000000000000000000000000001100 Z
b00000000000000000000000000011000 [
b00000000000000000000000000001100 \
#29
0T
#30
b00000000000000000000000000000000 C
0D
1F
b000 G
1H
b00000 J
b01010 K
b00000000000000000000000000000000 M
b00000000000001011000010100010011 N
b00 O
b0010011 P
b000 Q
0R
b10010000 S
1T
b00000000000000000000000000001100 X
b00000000000000000000000000010000 Z
b00000000000000000000000000010000 [
#31
0T
#32
b00000000000000000000000000000001 C
b00001 J
b01011 K
b00000000000101011000010110010011 N
1T
b00000000000000000000000000010000 X
b00000000000000000000000000010100 Z
b00000000000000000000000000010100 [
b00000000000000000000000000010001 \
#33
0T
#34
b11111111111111111111111111111000 C
1D
0F
b001 G
0H
b00110 J
b11001 K
b11111111111111111111111111111000 M
b11111110011001011001110011100011 N
b10 O
b1100011 P
b001 Q
1R
b01000011 S
1T
b00000000000000000000000000010100 X
b00000000000000000000000000001100 Z
b00000000000000000000000000011000 [
b00000000000000000000000000001100 \
#35
0T
#36
b00000000000000000000000000000000 C
0D
1F
b000 G
1H
b00000 J
b01010 K
b00000000000000000000000000000000 M
b00000000000001011000010100010011 N
b00 O
b0010011 P
b000 Q
0R
b10010000 S
1T
b00000000000000000000000000001100 X
b00000000000000000000000000010000 Z
b00000000000000000000000000010000 [
#37
0T
#38
b00000000000000000000000000000001 C
b00001 J
b01011 K
b00000000000101011000010110010011 N
1T
b00000000000000000000000000010000 X
b00000000000000000000000000010100 Z
b00000000000000000000000000010100 [
b00000000000000000000000000010001 \
#39
0T
#40
b11111111111111111111111111111000 C
1D
0F
b001 G
0H
b00110 J
b11001 K
b11111111111111111111111111111000 M
b11111110011001011001110011100011 N
b10 O
b1100011 P
b001 Q
1R
b01000011 S
1T
b00000000000000000000000000010100 X
b00000000000000000000000000001100 Z
b00000000000000000000000000011000 [
b00000000000000000000000000001100 \
#41
0T
#42
b00000000000000000000000000000000 C
0D
1F
b000 G
1H
b00000 J
b01010 K
b00000000000000000000000000000000 M
b00000000000001011000010100010011 N
b00 O
b0010011 P
b000 Q
0R
b10010000 S
1T
b00000000000000000000000000001100 X
b00000000000000000000000000010000 Z
b00000000000000000000000000010000 [
#43
0T
#44
b00000000000000000000000000000001 C
b00001 J
b01011 K
b00000000000101011000010110010011 N
1T
b00000000000000000000000000010000 X
b00000000000000000000000000010100 Z
b00000000000000000000000000010100 [
b00000000000000000000000000010001 \
#45
0T
#46
b11111111111111111111111111111000 C
1D
0F
b001 G
0H
b00110 J
b11001 K
b11111111111111111111111111111000 M
b11111110011001011001110011100011 N
b10 O
b1100011 P
b001 Q
1R
b01000011 S
1T
b00000000000000000000000000010100 X
b00000000000000000000000000001100 Z
b00000000000000000000000000011000 [
b00000000000000000000000000001100 \
#47
0T
#48
b00000000000000000000000000000000 C
0D
1F
b000 G
1H
b00000 J
b01010 K
b00000000000000000000000000000000 M
b00000000000001011000010100010011 N
b00 O
b0010011 P
b000 Q
0R
b10010000 S
1T
b00000000000000000000000000001100 X
b00000000000000000000000000010000 Z
b00000000000000000000000000010000 [
#49
0T
#50
b00000000000000000000000000000001 C
b00001 J
b01011 K
b00000000000101011000010110010011 N
1T
b00000000000000000000000000010000 X
b00000000000000000000000000010100 Z
b00000000000000000000000000010100 [
b00000000000000000000000000010001 \
#51
0T
#52
b11111111111111111111111111111000 C
1D
0F
b001 G
0H
b00110 J
b11001 K
b11111111111111111111111111111000 M
b11111110011001011001110011100011 N
b10 O
b1100011 P
b001 Q
1R
b01000011 S
1T
b00000000000000000000000000010100 X
b00000000000000000000000000001100 Z
b00000000000000000000000000011000 [
b00000000000000000000000000001100 \
#53
0T
#54
b00000000000000000000000000000000 C
0D
1F
b000 G
1H
b00000 J
b01010 K
b00000000000000000000000000000000 M
b00000000000001011000010100010011 N
b00 O
b0010011 P
b000 Q
0R
b10010000 S
1T
b00000000000000000000000000001100 X
b00000000000000000000000000010000 Z
b00000000000000000000000000010000 [
#55
0T
#56
b00000000000000000000000000000001 C
b00001 J
b01011 K
b00000000000101011000010110010011 N
1T
b00000000000000000000000000010000 X
b00000000000000000000000000010100 Z
b00000000000000000000000000010100 [
b00000000000000000000000000010001 \
#57
0T
#58
b11111111111111111111111111111000 C
1D
0F
b001 G
0H
b00110 J
b11001 K
b11111111111111111111111111111000 M
b11111110011001011001110011100011 N
b10 O
b1100011 P
b001 Q
1R
b01000011 S
1T
b00000000000000000000000000010100 X
b00000000000000000000000000001100 Z
b00000000000000000000000000011000 [
b00000000000000000000000000001100 \
#59
0T
#60
b00000000000000000000000000000000 C
0D
1F
b000 G
1H
b00000 J
b01010 K
b00000000000000000000000000000000 M
b00000000000001011000010100010011 N
b00 O
b0010011 P
b000 Q
0R
b10010000 S
1T
b00000000000000000000000000001100 X
b00000000000000000000000000010000 Z
b00000000000000000000000000010000 [
#61
0T
#62
b00000000000000000000000000000001 C
b00001 J
b01011 K
b00000000000101011000010110010011 N
1T
b00000000000000000000000000010000 X
b00000000000000000000000000010100 Z
b00000000000000000000000000010100 [
b00000000000000000000000000010001 \
#63
0T
#64
b11111111111111111111111111111000 C
1D
0F
b001 G
0H
b00110 J
b11001 K
b11111111111111111111111111111000 M
b11111110011001011001110011100011 N
b10 O
b1100011 P
b001 Q
1R
b01000011 S
1T
b00000000000000000000000000010100 X
b00000000000000000000000000001100 Z
b00000000000000000000000000011000 [
b00000000000000000000000000001100 \
#65
0T
#66
b00000000000000000000000000000000 C
0D
1F
b000 G
1H
b00000 J
b01010 K
b00000000000000000000000000000000 M
b00000000000001011000010100010011 N
b00 O
b0010011 P
b000 Q
0R
b10010000 S
1T
b00000000000000000000000000001100 X
b00000000000000000000000000010000 Z
b00000000000000000000000000010000 [
#67
0T
#68
b00000000000000000000000000000001 C
b00001 J
b01011 K
b00000000000101011000010110010011 N
1T
b00000000000000000000000000010000 X
b00000000000000000000000000010100 Z
b00000000000000000000000000010100 [
b00000000000000000000000000010001 \
#69
0T
#70
b11111111111111111111111111111000 C
1D
0F
b001 G
0H
b00110 J
b11001 K
b11111111111111111111111111111000 M
b11111110011001011001110011100011 N
b10 O
b1100011 P
b001 Q
1R
b01000011 S
1T
b00000000000000000000000000010100 X
b00000000000000000000000000001100 Z
b00000000000000000000000000011000 [
b00000000000000000000000000001100 \
#71
0T
#72
b00000000000000000000000000000000 C
0D
1F
b000 G
1H
b00000 J
b01010 K
b00000000000000000000000000000000 M
b00000000000001011000010100010011 N
b00 O
b0010011 P
b000 Q
0R
b10010000 S
1T
b00000000000000000000000000001100 X
b00000000000000000000000000010000 Z
b00000000000000000000000000010000 [
#73
0T
#74
b00000000000000000000000000000001 C
b00001 J
b01011 K
b00000000000101011000010110010011 N
1T
b00000000000000000000000000010000 X
b00000000000000000000000000010100 Z
b00000000000000000000000000010100 [
b00000000000000000000000000010001 \
#75
0T
#76
b11111111111111111111111111111000 C
1D
0F
b001 G
0H
b00110 J
b11001 K
b11111111111111111111111111111000 M
b11111110011001011001110011100011 N
b10 O
b1100011 P
b001 Q
1R
b01000011 S
1T
b00000000000000000000000000010100 X
b00000000000000000000000000001100 Z
b00000000000000000000000000011000 [
b00000000000000000000000000001100 \
#77
0T
#78
b00000000000000000000000000000000 C
0D
1F
b000 G
1H
b00000 J
b01010 K
b00000000000000000000000000000000 M
b00000000000001011000010100010011 N
b00 O
b0010011 P
b000 Q
0R
b10010000 S
1T
b00000000000000000000000000001100 X
b00000000000000000000000000010000 Z
b00000000000000000000000000010000 [
#79
0T
#80
b00000000000000000000000000000001 C
b00001 J
b01011 K
b00000000000101011000010110010011 N
1T
b00000000000000000000000000010000 X
b00000000000000000000000000010100 Z
b00000000000000000000000000010100 [
b00000000000000000000000000010001 \
#81
0T
#82
b11111111111111111111111111111000 C
1D
0F
b001 G
0H
b00110 J
b11001 K
b11111111111111111111111111111000 M
b11111110011001011001110011100011 N
b10 O
b1100011 P
b001 Q
1R
b01000011 S
1T
b00000000000000000000000000010100 X
b00000000000000000000000000001100 Z
b00000000000000000000000000011000 [
b00000000000000000000000000001100 \
#83
0T
#84
b00000000000000000000000000000000 C
0D
1F
b000 G
1H
b00000 J
b01010 K
b00000000000000000000000000000000 M
b00000000000001011000010100010011 N
b00 O
b0010011 P
b000 Q
0R
b10010000 S
1T
b00000000000000000000000000001100 X
b00000000000000000000000000010000 Z
b00000000000000000000000000010000 [
#85
0T
#86
b00000000000000000000000000000001 C
b00001 J
b01011 K
b00000000000101011000010110010011 N
1T
b00000000000000000000000000010000 X
b00000000000000000000000000010100 Z
b00000000000000000000000000010100 [
b00000000000000000000000000010001 \
#87
0T
#88
b11111111111111111111111111111000 C
1D
0F
b001 G
0H
b00110 J
b11001 K
b11111111111111111111111111111000 M
b11111110011001011001110011100011 N
b10 O
b1100011 P
b001 Q
1R
b01000011 S
1T
b00000000000000000000000000010100 X
b00000000000000000000000000001100 Z
b00000000000000000000000000011000 [
b00000000000000000000000000001100 \
#89
0T
#90
b00000000000000000000000000000000 C
0D
1F
b000 G
1H
b00000 J
b01010 K
b00000000000000000000000000000000 M
b00000000000001011000010100010011 N
b00 O
b0010011 P
b000 Q
0R
b10010000 S
1T
b00000000000000000000000000001100 X
b00000000000000000000000000010000 Z
b00000000000000000000000000010000 [
#91
0T
#92
b00000000000000000000000000000001 C
b00001 J
b01011 K
b00000000000101011000010110010011 N
1T
b00000000000000000000000000010000 X
b00000000000000000000000000010100 Z
b00000000000000000000000000010100 [
b00000000000000000000000000010001 \
#93
0T
#94
b11111111111111111111111111111000 C
1D
0F
b001 G
0H
b00110 J
b11001 K
b11111111111111111111111111111000 M
b11111110011001011001110011100011 N
b10 O
b1100011 P
b001 Q
1R
b01000011 S
1T
b00000000000000000000000000010100 X
b00000000000000000000000000001100 Z
b00000000000000000000000000011000 [
b00000000000000000000000000001100 \
#95
0T
#96
b00000000000000000000000000000000 C
0D
1F
b000 G
1H
b00000 J
b01010 K
b00000000000000000000000000000000 M
b00000000000001011000010100010011 N
b00 O
b0010011 P
b000 Q
0R
b10010000 S
1T
b00000000000000000000000000001100 X
b00000000000000000000000000010000 Z
b00000000000000000000000000010000 [
#97
0T
#98
b00000000000000000000000000000001 C
b00001 J
b01011 K
b00000000000101011000010110010011 N
1T
b00000000000000000000000000010000 X
b00000000000000000000000000010100 Z
b00000000000000000000000000010100 [
b00000000000000000000000000010001 \
#99
0T
#100
b11111111111111111111111111111000 C
1D
0F
b001 G
0H
b00110 J
b11001 K
b11111111111111111111111111111000 M
b11111110011001011001110011100011 N
b10 O
b1100011 P
b001 Q
1R
b01000011 S
1T
b00000000000000000000000000010100 X
b00000000000000000000000000001100 Z
b00000000000000000000000000011000 [
b00000000000000000000000000001100 \
#101
0T
